ark/__init__.py
ark/_ark.py
ark/_helpers.py
ark/config.py
ark/exceptions.py
ark/py.typed
ark/state.py
ark/tools.py
ark/window.py
ark/assets/buffs/broken_bones.png
ark/assets/buffs/hungry.png
ark/assets/buffs/pod_buff.png
ark/assets/buffs/tek_pod_xp_buff.png
ark/assets/buffs/thirsty.png
ark/assets/interfaces/bed_button.png
ark/assets/interfaces/bed_button_corner.png
ark/assets/interfaces/bed_filter.png
ark/assets/interfaces/bed_icon.png
ark/assets/interfaces/bed_x.png
ark/assets/interfaces/cancel_craft.png
ark/assets/interfaces/capped.png
ark/assets/interfaces/crafting.png
ark/assets/interfaces/day.png
ark/assets/interfaces/folder_AAA.png
ark/assets/interfaces/folder_BBB.png
ark/assets/interfaces/folder_CCC.png
ark/assets/interfaces/folder_DDD.png
ark/assets/interfaces/folder_EEE.png
ark/assets/interfaces/folder_FFF.png
ark/assets/interfaces/folder_GGG.png
ark/assets/interfaces/folder_HHH.png
ark/assets/interfaces/folder_III.png
ark/assets/interfaces/folder_JJJ.png
ark/assets/interfaces/folder_KKK.png
ark/assets/interfaces/folder_view.png
ark/assets/interfaces/forge_full.png
ark/assets/interfaces/grind_all_items.png
ark/assets/interfaces/inventory.png
ark/assets/interfaces/joining_failed.png
ark/assets/interfaces/level_up.png
ark/assets/interfaces/main_menu_accept.png
ark/assets/interfaces/main_menu_options.png
ark/assets/interfaces/online.png
ark/assets/interfaces/random_location.png
ark/assets/interfaces/remote_inventory.png
ark/assets/interfaces/resume.png
ark/assets/interfaces/server_favorite.png
ark/assets/interfaces/session_list.png
ark/assets/interfaces/show_engrams.png
ark/assets/interfaces/timer.png
ark/assets/interfaces/toggle_online_members.png
ark/assets/interfaces/tool_tips_enabled.png
ark/assets/interfaces/tribe_log.png
ark/assets/interfaces/turn_off.png
ark/assets/interfaces/turn_on.png
ark/assets/interfaces/unlearned_engrams.png
ark/assets/interfaces/vault_capped.png
ark/assets/interfaces/vault_full.png
ark/assets/items/arb_icon.png
ark_api-1.3.3.dist-info/LICENSE
ark_api-1.3.3.dist-info/METADATA
ark_api-1.3.3.dist-info/WHEEL
ark_api-1.3.3.dist-info/top_level.txt
ark_api-1.3.3.dist-info/RECORD
